systema/__init__.py
systema/__main__.py
systema/__version__.py
systema/cli.py
systema/server/__init__.py
systema/server/db.py
systema/server/main.py
systema/server/project_manager/endpoints.py
systema/server/project_manager/models.py
systema-0.5.1.dist-info/METADATA
systema-0.5.1.dist-info/WHEEL
systema-0.5.1.dist-info/entry_points.txt
systema-0.5.1.dist-info/RECORD
