Metadata-Version: 2.1
Name: systema
Version: 0.5.1
Summary: 
Author: Rodrigo Eiti Kimura
Author-email: rodrigoeitikimura@gmail.com
Requires-Python: >=3.11,<4.0
Classifier: Programming Language :: Python :: 3
Classifier: Programming Language :: Python :: 3.11
Classifier: Programming Language :: Python :: 3.12
Requires-Dist: fastapi[all] (>=0.109.2,<0.110.0)
Requires-Dist: sqlmodel (>=0.0.16,<0.0.17)
Requires-Dist: typer[all] (>=0.9.0,<0.10.0)
